{"otherData": {},"traceEvents":[,{"cat":"function","dur":55157,"name":"WindowsWindow::Init()->glfwInit()","ph":"X","pid":0,"tid":880555966,"ts":264850314392.100},{"cat":"function","dur":166383,"name":"WindowsWindow::Init()->glfwCreateWindow()","ph":"X","pid":0,"tid":880555966,"ts":264850369878.200},{"cat":"function","dur":3033,"name":"void IE::OpenGLContext::Init(void)","ph":"X","pid":0,"tid":880555966,"ts":264850536428.200},{"cat":"function","dur":25,"name":"void IE::WindowsWindow::SetVSync(bool)","ph":"X","pid":0,"tid":880555966,"ts":264850539565.000},{"cat":"function","dur":226479,"name":"void IE::WindowsWindow::Init(const struct IE::WindowProps &)","ph":"X","pid":0,"tid":880555966,"ts":264850313169.900},{"cat":"function","dur":226529,"name":"IE::WindowsWindow::WindowsWindow(const struct IE::WindowProps &)","ph":"X","pid":0,"tid":880555966,"ts":264850313166.800},{"cat":"function","dur":226590,"name":"class std::unique_ptr<class IE::Window,struct std::default_delete<class IE::Window> > IE::Window::Create(const struct IE::WindowProps &)","ph":"X","pid":0,"tid":880555966,"ts":264850313155.700},{"cat":"function","dur":10,"name":"void IE::WindowsWindow::SetVSync(bool)","ph":"X","pid":0,"tid":880555966,"ts":264850539806.400},{"cat":"function","dur":4,"name":"void IE::OpenGLRendererAPI::Init(void)","ph":"X","pid":0,"tid":880555966,"ts":264850539876.700},{"cat":"function","dur":63,"name":"void IE::RenderCommand::Init(void)","ph":"X","pid":0,"tid":880555966,"ts":264850539869.900},{"cat":"function","dur":21,"name":"IE::OpenGLVertexArray::OpenGLVertexArray(void)","ph":"X","pid":0,"tid":880555966,"ts":264850540002.300},{"cat":"function","dur":11,"name":"IE::OpenGLVertexBuffer::OpenGLVertexBuffer(unsigned int)","ph":"X","pid":0,"tid":880555966,"ts":264850540100.500},{"cat":"function","dur":0,"name":"void IE::OpenGLVertexBuffer::Bind(void) const","ph":"X","pid":0,"tid":880555966,"ts":264850540230.100},{"cat":"function","dur":91,"name":"void IE::OpenGLVertexArray::AddVertexBuffer(const class std::shared_ptr<class IE::VertexBuffer> &)","ph":"X","pid":0,"tid":880555966,"ts":264850540190.900},{"cat":"function","dur":71,"name":"IE::OpenGLIndexBuffer::OpenGLIndexBuffer(unsigned int *,unsigned int)","ph":"X","pid":0,"tid":880555966,"ts":264850540726.700},{"cat":"function","dur":1,"name":"void IE::OpenGLIndexBuffer::Bind(void) const","ph":"X","pid":0,"tid":880555966,"ts":264850540841.800},{"cat":"function","dur":39,"name":"void IE::OpenGLVertexArray::SetIndexBuffer(const class std::shared_ptr<class IE::IndexBuffer> &)","ph":"X","pid":0,"tid":880555966,"ts":264850540841.500},{"cat":"function","dur":373,"name":"IE::OpenGLTextures2D::OpenGLTextures2D(unsigned int,unsigned int)","ph":"X","pid":0,"tid":880555966,"ts":264850540924.700},{"cat":"function","dur":8,"name":"void IE::OpenGLTextures2D::SetData(void *,unsigned int)","ph":"X","pid":0,"tid":880555966,"ts":264850541344.600},{"cat":"function","dur":161,"name":"class std::basic_string<char,struct std::char_traits<char>,class std::allocator<char> > IE::OpenGLShader::ReadShaderFile(const class std::basic_string<char,struct std::char_traits<char>,class std::allocator<char> > &)","ph":"X","pid":0,"tid":880555966,"ts":264850541424.800},{"cat":"function","dur":53,"name":"class std::unordered_map<unsigned int,class std::basic_string<char,struct std::char_traits<char>,class std::allocator<char> >,struct std::hash<unsigned int>,struct std::equal_to<unsigned int>,class std::allocator<struct std::pair<unsigned int const ,class std::basic_string<char,struct std::char_traits<char>,class std::allocator<char> > > > > IE::OpenGLShader::PreProcessShaderSrc(const class std::basic_string<char,struct std::char_traits<char>,class std::allocator<char> > &)","ph":"X","pid":0,"tid":880555966,"ts":264850541646.500},{"cat":"function","dur":52877,"name":"void IE::OpenGLShader::CompileGLShader(const class std::unordered_map<unsigned int,class std::basic_string<char,struct std::char_traits<char>,class std::allocator<char> >,struct std::hash<unsigned int>,struct std::equal_to<unsigned int>,class std::allocator<struct std::pair<unsigned int const ,class std::basic_string<char,struct std::char_traits<char>,class std::allocator<char> > > > > &)","ph":"X","pid":0,"tid":880555966,"ts":264850541753.200},{"cat":"function","dur":53431,"name":"IE::OpenGLShader::OpenGLShader(const class std::basic_string<char,struct std::char_traits<char>,class std::allocator<char> > &)","ph":"X","pid":0,"tid":880555966,"ts":264850541418.700},{"cat":"function","dur":2,"name":"void IE::OpenGLShader::Bind(void) const","ph":"X","pid":0,"tid":880555966,"ts":264850594916.300},{"cat":"function","dur":55040,"name":"void IE::Renderer2D::Init(void)","ph":"X","pid":0,"tid":880555966,"ts":264850539980.900},{"cat":"function","dur":55195,"name":"void IE::Renderer::Init(void)","ph":"X","pid":0,"tid":880555966,"ts":264850539869.700},{"cat":"function","dur":734,"name":"void IE::Application::PushOverlay(class IE::Layer *)","ph":"X","pid":0,"tid":880555966,"ts":264850595111.000},{"cat":"function","dur":282753,"name":"IE::Application::Application(const class std::basic_string<char,struct std::char_traits<char>,class std::allocator<char> > &)","ph":"X","pid":0,"tid":880555966,"ts":264850313150.700},{"cat":"function","dur":6,"name":"IE::OrthographicCamera::OrthographicCamera(float,float,float,float)","ph":"X","pid":0,"tid":880555966,"ts":264850595962.400},{"cat":"function","dur":0,"name":"IE::IsoEditorLayer::IsoEditorLayer(void)","ph":"X","pid":0,"tid":880555966,"ts":264850596014.400},{"cat":"function","dur":174527,"name":"OpenGLTextures2D::OpenGLTextures2D(const std::string& path) -> stbi_load","ph":"X","pid":0,"tid":880555966,"ts":264850596069.500},{"cat":"function","dur":182835,"name":"IE::OpenGLTextures2D::OpenGLTextures2D(const class std::basic_string<char,struct std::char_traits<char>,class std::allocator<char> > &)","ph":"X","pid":0,"tid":880555966,"ts":264850596063.700},{"cat":"function","dur":185055,"name":"void IE::IsoEditorLayer::OnAttach(void)","ph":"X","pid":0,"tid":880555966,"ts":264850596059.400},{"cat":"function","dur":185137,"name":"void IE::Application::PushLayer(class IE::Layer *)","ph":"X","pid":0,"tid":880555966,"ts":264850596055.100}]}